[
  {
    "id": 3,
    "name": "котик вислоух лох",
    "price": 150,
    "description": "пушистое чудо",
    "category": "cat2"
  },
  {
    "id": 4,
    "name": "котик оранжевый",
    "price": 300,
    "description": "пушистое чудо",
    "category": "cat2"
  },
  {
    "id": 5,
    "name": "котик белый",
    "price": 250,
    "description": "пушистое чудо",
    "category": "cat, cat2"
  },
  {
    "name": "котик пушистый",
    "price": 100,
    "description": "добавленный котик",
    "category": "cat2"
  }
]